em27_metadata-1.3.0.dist-info/METADATA
em27_metadata-1.3.0.dist-info/WHEEL
em27_metadata-1.3.0.dist-info/entry_points.txt
em27_metadata-1.3.0.dist-info/licenses/LICENSE
em27_metadata/__init__.py
em27_metadata/interfaces.py
em27_metadata/loader.py
em27_metadata/py.typed
em27_metadata/sample_data/.prettierrc
em27_metadata/sample_data/README.md
em27_metadata/sample_data/campaigns.json
em27_metadata/sample_data/events.json
em27_metadata/sample_data/locations.json
em27_metadata/sample_data/sensors.json
em27_metadata/types.py
em27_metadata-1.3.0.dist-info/RECORD
