Metadata-Version: 2.1
Name: em27_metadata
Version: 1.3.0
Summary: Single source of truth for ESM's EM27 measurement logistics
Author-Email: Moritz Makowski <moritz.makowski@tum.de>, =?utf-8?q?Marlon_M=C3=BCller?= <marlon.mueller@tum.de>
License: MIT
Classifier: License :: OSI Approved :: MIT License
Classifier: Programming Language :: Python :: 3
Classifier: Programming Language :: Python :: 3.10
Classifier: Programming Language :: Python :: 3.11
Classifier: Programming Language :: Python :: 3.12
Project-URL: repository, https://github.com/tum-esm/em27-metadata
Project-URL: documentation, https://em27-retrieval-pipeline.netlify.app/
Requires-Python: <4.0,>=3.10
Requires-Dist: requests>=2.32.5
Requires-Dist: pydantic>=2.12.3
Requires-Dist: tum-esm-utils>=2.10.0
Requires-Dist: ruff>=0.14.3
Provides-Extra: dev
Requires-Dist: pytest>=7.4.4; extra == "dev"
Requires-Dist: mypy>=1.8.0; extra == "dev"
Requires-Dist: types-requests>=2.31.0.20240125; extra == "dev"
Requires-Dist: python-dotenv>=1.0.1; extra == "dev"
Requires-Dist: ruff>=0.14.3; extra == "dev"
Requires-Dist: pyright>=1.1.407; extra == "dev"
